bayinx/__init__.py
bayinx/ops.py
bayinx/posterior.py
bayinx/constraints/__init__.py
bayinx/constraints/identity.py
bayinx/constraints/interval.py
bayinx/constraints/lower.py
bayinx/constraints/upper.py
bayinx/core/__init__.py
bayinx/core/constraint.py
bayinx/core/context.py
bayinx/core/distribution.py
bayinx/core/flow.py
bayinx/core/model.py
bayinx/core/node.py
bayinx/core/types.py
bayinx/core/utils.py
bayinx/core/variational.py
bayinx/dists/__init__.py
bayinx/dists/_bernoulli.py
bayinx/dists/_binomial.py
bayinx/dists/_exponential.py
bayinx/dists/_normal.py
bayinx/dists/_poisson.py
bayinx/dists/bernoulli/__init__.py
bayinx/dists/bernoulli/distribution.py
bayinx/dists/bernoulli/pars/__init__.py
bayinx/dists/bernoulli/pars/prob_failure.py
bayinx/dists/bernoulli/pars/prob_success.py
bayinx/dists/binomial/__init__.py
bayinx/dists/binomial/distribution.py
bayinx/dists/binomial/pars/__init__.py
bayinx/dists/binomial/pars/prob_failure.py
bayinx/dists/binomial/pars/prob_success.py
bayinx/dists/exponential/__init__.py
bayinx/dists/exponential/distribution.py
bayinx/dists/exponential/pars/__init__.py
bayinx/dists/exponential/pars/rate.py
bayinx/dists/exponential/pars/scale.py
bayinx/dists/normal/__init__.py
bayinx/dists/normal/distribution.py
bayinx/dists/normal/pars/__init__.py
bayinx/dists/normal/pars/mean_prec.py
bayinx/dists/normal/pars/mean_scale.py
bayinx/dists/normal/pars/mean_var.py
bayinx/dists/poisson/__init__.py
bayinx/dists/poisson/distribution.py
bayinx/dists/poisson/pars/__init__.py
bayinx/dists/poisson/pars/log_rate.py
bayinx/dists/poisson/pars/rate.py
bayinx/flows/__init__.py
bayinx/flows/diagaffine.py
bayinx/flows/fullaffine.py
bayinx/flows/lowrankaffine.py
bayinx/flows/otflow.py
bayinx/flows/planar.py
bayinx/flows/radial.py
bayinx/flows/sylvester.py
bayinx/nodes/__init__.py
bayinx/nodes/continuous.py
bayinx/nodes/observed.py
bayinx/nodes/stochastic.py
bayinx/vi/__init__.py
bayinx/vi/meanfield.py
bayinx/vi/normalizing_flow.py
bayinx/vi/standard.py
bayinx-0.5.8.dist-info/METADATA
bayinx-0.5.8.dist-info/WHEEL
bayinx-0.5.8.dist-info/licenses/LICENSE
bayinx-0.5.8.dist-info/RECORD
