Metadata-Version: 2.4
Name: bayinx
Version: 0.5.8
Summary: Bayesian Inference with JAX
Author: Todd Pocuca
Maintainer: Todd Pocuca
License-File: LICENSE
Requires-Python: >=3.12
Requires-Dist: diffrax>=0.7.0
Requires-Dist: equinox>=0.13.2
Requires-Dist: jax>=0.8.0
Requires-Dist: jaxtyping>=0.2.36
Requires-Dist: optax>=0.2.4
